simple_factory_pattern/__init__.py
simple_factory_pattern/factorypattern_meta.py
simple_factory_pattern/py.typed
simple_factory_pattern-2.0.0.dist-info/LICENSE
simple_factory_pattern-2.0.0.dist-info/METADATA
simple_factory_pattern-2.0.0.dist-info/WHEEL
simple_factory_pattern-2.0.0.dist-info/RECORD
